pip_upgrader/__init__.py
pip_upgrader/cli.py
pip_upgrader/packages_detector.py
pip_upgrader/packages_interactive_selector.py
pip_upgrader/packages_status_detector.py
pip_upgrader/packages_upgrader.py
pip_upgrader/requirements_detector.py
pip_upgrader/virtualenv_checker.py
pip_upgrader-1.4.15.dist-info/LICENSE
pip_upgrader-1.4.15.dist-info/METADATA
pip_upgrader-1.4.15.dist-info/WHEEL
pip_upgrader-1.4.15.dist-info/entry_points.txt
pip_upgrader-1.4.15.dist-info/top_level.txt
pip_upgrader-1.4.15.dist-info/RECORD
