Metadata-Version: 2.1
Name: pip_upgrader
Version: 1.4.15
Summary: An interactive pip requirements upgrader. It also updates the version in your requirements.txt file.
Home-page: https://github.com/simion/pip-upgrader
Author: Simion Baws
Author-email: simion.agv@gmail.com
License: Apache License 2.0
Keywords: cli,pip,pypi,requirements,upgrade
Platform: UNKNOWN
Classifier: Intended Audience :: Developers
Classifier: Topic :: Utilities
Classifier: License :: Public Domain
Classifier: Natural Language :: English
Classifier: Operating System :: OS Independent
Classifier: Programming Language :: Python :: 2
Classifier: Programming Language :: Python :: 2.6
Classifier: Programming Language :: Python :: 2.7
Classifier: Programming Language :: Python :: 3
Classifier: Programming Language :: Python :: 3.2
Classifier: Programming Language :: Python :: 3.3
Classifier: Programming Language :: Python :: 3.4
Classifier: Programming Language :: Python :: 3.5
Classifier: Programming Language :: Python :: 3.6
Provides-Extra: test
